<pair-comparison><technical><summary name="EUR/USD - Euro US Dollar">1.1312 +0.0019 &#160;&#160; +0.17% </summary><summary>Prev. Close: 1.1292 Bid/Ask:  1.1311 1.1312 Day's Range: 1.1215 - 1.1338 </summary><advice>BUY</advice><Moving_Averages><Moving_Averages>Moving Averages:</Moving_Averages><Moving_Averages>BUY</Moving_Averages><Moving_Averages>(8)</Moving_Averages><Moving_Averages>(4)</Moving_Averages></Moving_Averages><Technical_Indicators><Technical_Indicators>Technical Indicators:</Technical_Indicators><Technical_Indicators>BUY</Technical_Indicators><Technical_Indicators>(3)</Technical_Indicators><Technical_Indicators>(2)</Technical_Indicators></Technical_Indicators><Pivot_Points><value name="Name">Classic</value><value name="S3">1.1279</value><value name="S2">1.1290</value><value name="S1">1.1301</value><value name="Pivot Points">1.1312</value><value name="R1">1.1323</value><value name="R2">1.1334</value><value name="R3">1.1345</value><value name="Name">Fibonacci</value><value name="S3">1.1290</value><value name="S2">1.1298</value><value name="S1">1.1304</value><value name="Pivot Points">1.1312</value><value name="R1">1.1320</value><value name="R2">1.1326</value><value name="R3">1.1334</value><value name="Name">Camarilla</value><value name="S3">1.1305</value><value name="S2">1.1307</value><value name="S1">1.1309</value><value name="Pivot Points">1.1312</value><value name="R1">1.1313</value><value name="R2">1.1315</value><value name="R3">1.1317</value><value name="Name">Woodie's</value><value name="S3">1.1279</value><value name="S2">1.1290</value><value name="S1">1.1301</value><value name="Pivot Points">1.1312</value><value name="R1">1.1323</value><value name="R2">1.1334</value><value name="R3">1.1345</value><value name="Name">DeMark's</value><value name="S3">-</value><value name="S2">-</value><value name="S1">1.1306</value><value name="Pivot Points">1.1315</value><value name="R1">1.1328</value><value name="R2">-</value><value name="R3">-</value></Pivot_Points><Technical_Indicators><value name="Name">RSI(14) </value><value name="Value">53.886</value><value name="Action">Neutral</value><value name="Name">STOCH(9,6) </value><value name="Value">54.267</value><value name="Action">Neutral</value><value name="Name">STOCHRSI(14) </value><value name="Value">17.036</value><value name="Action">Oversold</value><value name="Name">MACD(12,26) </value><value name="Value">0.001</value><value name="Action">Buy</value><value name="Name">ADX(14) </value><value name="Value">23.951</value><value name="Action">Sell</value><value name="Name">Williams %R </value><value name="Value">-47.170</value><value name="Action">Neutral</value><value name="Name">CCI(14) </value><value name="Value">5.6866</value><value name="Action">Neutral</value><value name="Name">ATR(14) </value><value name="Value">0.0017</value><value name="Action">High Volatility</value><value name="Name">Highs/Lows(14) </value><value name="Value">0.0000</value><value name="Action">Neutral</value><value name="Name">Ultimate Oscillator </value><value name="Value">47.692</value><value name="Action">Sell</value><value name="Name">ROC </value><value name="Value">0.062</value><value name="Action">Buy</value><value name="Name">Bull/Bear Power(13) </value><value name="Value">0.0006</value><value name="Action">Buy</value><value name="Summary">Buy: 3 Sell: 2 Neutral: 7</value></Technical_Indicators><Moving_Averages><value name="Period">MA5 </value><value name="Simple">1.1316 Sell</value><value name="Exceptional">1.1314 Sell</value><value name="Period">MA10 </value><value name="Simple">1.1319 Sell</value><value name="Exceptional">1.1313 Sell</value><value name="Period">MA20 </value><value name="Simple">1.1308 Buy</value><value name="Exceptional">1.1307 Buy</value><value name="Period">MA50 </value><value name="Simple">1.1288 Buy</value><value name="Exceptional">1.1301 Buy</value><value name="Period">MA100 </value><value name="Simple">1.1304 Buy</value><value name="Exceptional">1.1286 Buy</value><value name="Period">MA200 </value><value name="Simple">1.1254 Buy</value><value name="Exceptional">1.1273 Buy</value><value name="Period">
 Buy:</value><value name="Summary">Buy: 8 Sell: 4 Neutral: 0</value></Moving_Averages></technical></pair-comparison>